{
  "task_id": "task1_bug_triage",
  "task_name": "Bug Triage Sprint",
  "task_description": "Nexus Analytics received 10 bug reports this week. As PM, assign a priority (P0=Critical/fix now, P1=This sprint, P2=Next sprint, P3=Backlog) to every bug. You have 20 steps. Use 'prioritize' actions on each item, then 'submit' to finalize.",
  "difficulty": "easy",
  "max_steps": 20,
  "sprint_capacity": 30,
  "context": {
    "company": "Nexus Analytics",
    "product": "B2B analytics dashboard (SaaS)",
    "quarter_goal": "Reduce churn among enterprise customers by 15%",
    "note": "P0 items trigger immediate on-call pages. P1 items are committed this sprint. Triage must be accurate — wrong priorities erode team trust."
  },
  "items": [
    {
      "id": "BUG-001",
      "title": "Dashboard crashes on export for enterprise accounts > 1M rows",
      "description": "Users on enterprise plans with datasets larger than 1M rows get an unhandled exception when clicking 'Export to CSV'. Error: OOM in data serialization layer. Affects all export formats.",
      "type": "bug",
      "reporter": "Sarah (Enterprise CSM)",
      "severity": "critical",
      "user_impact": 2400,
      "effort_points": 5,
      "strategic_score": 0.9,
      "age_days": 2,
      "customer_tier": "enterprise",
      "stakeholder_votes": {"Sales": 5, "Support": 5, "Eng": 3},
      "tags": ["export", "data", "enterprise", "crash"],
      "dependencies": [],
      "revenue_impact_usd": 480000
    },
    {
      "id": "BUG-002",
      "title": "Free tier users see 'Upgrade' button in wrong locale (zh-CN)",
      "description": "The upgrade CTA button shows English text 'Upgrade Now' instead of Chinese for zh-CN locale users on the free tier plan page. Visual bug, no functional impact.",
      "type": "bug",
      "reporter": "Localization bot",
      "severity": "low",
      "user_impact": 310,
      "effort_points": 1,
      "strategic_score": 0.2,
      "age_days": 14,
      "customer_tier": "free",
      "stakeholder_votes": {"Growth": 1},
      "tags": ["i18n", "ui", "free-tier"],
      "dependencies": [],
      "revenue_impact_usd": null
    },
    {
      "id": "BUG-003",
      "title": "SSO login fails for Okta integrations when MFA is enforced",
      "description": "Enterprise customers using Okta SSO with MFA enforcement are unable to log in. Auth token exchange fails silently and users are redirected to homepage. Affects all Okta-based enterprise customers.",
      "type": "bug",
      "reporter": "James (Enterprise Support)",
      "severity": "critical",
      "user_impact": 1850,
      "effort_points": 8,
      "strategic_score": 0.95,
      "age_days": 1,
      "customer_tier": "enterprise",
      "stakeholder_votes": {"Sales": 5, "Support": 5, "Eng": 4},
      "tags": ["auth", "sso", "okta", "enterprise", "security"],
      "dependencies": [],
      "revenue_impact_usd": 920000
    },
    {
      "id": "BUG-004",
      "title": "Tooltip z-index overlaps modal on Safari 17",
      "description": "In Safari 17+, chart tooltips render above modal dialogs when a modal is open, causing visual overlap. No data loss, no functional regression. Reproducible only on macOS Safari 17.",
      "type": "bug",
      "reporter": "QA automation",
      "severity": "low",
      "user_impact": 90,
      "effort_points": 2,
      "strategic_score": 0.1,
      "age_days": 30,
      "customer_tier": "growth",
      "stakeholder_votes": {"Eng": 1},
      "tags": ["ui", "safari", "css"],
      "dependencies": [],
      "revenue_impact_usd": null
    },
    {
      "id": "BUG-005",
      "title": "Scheduled reports not delivered if recipient email has + alias",
      "description": "Scheduled PDF/CSV reports fail silently when the recipient email contains a + alias (e.g., user+reports@company.com). Email validation regex incorrectly rejects valid RFC 5321 addresses.",
      "type": "bug",
      "reporter": "Taylor (Growth CSM)",
      "severity": "medium",
      "user_impact": 430,
      "effort_points": 3,
      "strategic_score": 0.5,
      "age_days": 8,
      "customer_tier": "growth",
      "stakeholder_votes": {"Support": 3, "Growth": 2},
      "tags": ["email", "scheduled-reports", "regex"],
      "dependencies": [],
      "revenue_impact_usd": 28000
    },
    {
      "id": "BUG-006",
      "title": "API rate limiter returns 429 for valid requests under documented limit",
      "description": "The public API rate limiter is misconfigured and triggers 429 Too Many Requests for customers sending fewer than the documented 1000 req/min. Root cause: sliding window bug in Redis counter resets. Developer customers are filing complaints and threatening to churn.",
      "type": "bug",
      "reporter": "Dev Relations",
      "severity": "high",
      "user_impact": 780,
      "effort_points": 5,
      "strategic_score": 0.8,
      "age_days": 5,
      "customer_tier": "growth",
      "stakeholder_votes": {"Sales": 4, "Eng": 4, "Support": 3},
      "tags": ["api", "rate-limiting", "developer", "reliability"],
      "dependencies": [],
      "revenue_impact_usd": 156000
    },
    {
      "id": "BUG-007",
      "title": "Dark mode color contrast fails WCAG AA on secondary buttons",
      "description": "In dark mode, secondary action buttons (#6B7280 on #1F2937) have a contrast ratio of 3.1:1, below the WCAG AA minimum of 4.5:1. Affects accessibility compliance.",
      "type": "bug",
      "reporter": "Accessibility audit (automated)",
      "severity": "medium",
      "user_impact": 1200,
      "effort_points": 2,
      "strategic_score": 0.3,
      "age_days": 45,
      "customer_tier": "growth",
      "stakeholder_votes": {"Eng": 2},
      "tags": ["accessibility", "a11y", "dark-mode", "ui"],
      "dependencies": [],
      "revenue_impact_usd": null
    },
    {
      "id": "BUG-008",
      "title": "Data pipeline ingestion silently drops rows with null timestamps",
      "description": "The ETL pipeline silently discards rows where the timestamp field is null rather than raising an error or substituting a default. Enterprise customers running compliance reports notice missing records weeks later. No visibility into data loss.",
      "type": "bug",
      "reporter": "Marcus (Enterprise Eng)",
      "severity": "high",
      "user_impact": 3100,
      "effort_points": 8,
      "strategic_score": 0.85,
      "age_days": 3,
      "customer_tier": "enterprise",
      "stakeholder_votes": {"Sales": 4, "Support": 4, "Eng": 5},
      "tags": ["data", "pipeline", "etl", "data-integrity", "enterprise"],
      "dependencies": [],
      "revenue_impact_usd": 350000
    },
    {
      "id": "BUG-009",
      "title": "Onboarding checklist UI shows 100% complete when 3 steps remain",
      "description": "The onboarding progress checklist incorrectly calculates completion and shows 100% before all steps are done. New users think they're done but haven't connected a data source or set up their first dashboard.",
      "type": "bug",
      "reporter": "Growth team",
      "severity": "medium",
      "user_impact": 640,
      "effort_points": 3,
      "strategic_score": 0.6,
      "age_days": 12,
      "customer_tier": "free",
      "stakeholder_votes": {"Growth": 4, "Support": 2},
      "tags": ["onboarding", "ux", "activation"],
      "dependencies": [],
      "revenue_impact_usd": 85000
    },
    {
      "id": "BUG-010",
      "title": "Billing page throws 500 error when promo code field is left blank",
      "description": "On the subscription upgrade page, leaving the promo code field empty and clicking 'Apply' causes a 500 internal server error. The field should be optional. No charge occurs but user sees a generic error and often abandons checkout.",
      "type": "bug",
      "reporter": "Checkout funnel monitoring",
      "severity": "high",
      "user_impact": 920,
      "effort_points": 2,
      "strategic_score": 0.75,
      "age_days": 4,
      "customer_tier": "free",
      "stakeholder_votes": {"Growth": 5, "Sales": 3},
      "tags": ["billing", "checkout", "conversion", "500-error"],
      "dependencies": [],
      "revenue_impact_usd": 210000
    }
  ],
  "ground_truth_priorities": {
    "BUG-001": "P0",
    "BUG-002": "P3",
    "BUG-003": "P0",
    "BUG-004": "P3",
    "BUG-005": "P2",
    "BUG-006": "P1",
    "BUG-007": "P2",
    "BUG-008": "P0",
    "BUG-009": "P2",
    "BUG-010": "P1"
  }
}
